CHANGES.rst
LICENSE
MANIFEST.in
README.rst
distribute-0.6.10.tar.gz
requirements.txt
setup.py
stdeb.cfg
doc/conf.py
doc/dataobject.rst
doc/fields.rst
doc/http.rst
doc/index.rst
doc/promise.rst
doc/readme_from_docstring.py
doc/requirements.txt
doc/exts/document_init_methods.py
examples/couchdb.py
examples/giantbomb.py
examples/netflix.py
examples/twitter.py
remoteobjects/__init__.py
remoteobjects/dataobject.py
remoteobjects/fields.py
remoteobjects/http.py
remoteobjects/json.py
remoteobjects/listobject.py
remoteobjects/promise.py
remoteobjects.egg-info/PKG-INFO
remoteobjects.egg-info/SOURCES.txt
remoteobjects.egg-info/dependency_links.txt
remoteobjects.egg-info/requires.txt
remoteobjects.egg-info/top_level.txt
tests/__init__.py
tests/extra_dataobject.py
tests/requirements.txt
tests/test_dataobject.py
tests/test_http.py
tests/test_listobject.py
tests/test_promise.py
tests/test_remoteobject.py
tests/utils.py
tests/performance/benchmark_decoding.py
tests/performance/twiddle.json
tests/performance/twiddle.py