Metadata-Version: 1.1
Name: remoteobjects
Version: 1.2.1
Summary: an Object RESTational Model
Home-page: http://github.com/saymedia/remoteobjects
Author: SAY Media Ltd.
Author-email: python@saymedia.com
License: UNKNOWN
Platform: UNKNOWN
Classifier: Development Status :: 4 - Beta
Classifier: Environment :: Console
Classifier: Environment :: Web Environment
Classifier: Intended Audience :: Developers
Classifier: License :: OSI Approved :: BSD License
Classifier: Operating System :: MacOS :: MacOS X
Classifier: Operating System :: POSIX
Classifier: Programming Language :: Python
Classifier: Topic :: Internet :: WWW/HTTP
Classifier: Topic :: Software Development :: Object Brokering
Requires: simplejson(>=2.0.0)
Requires: httplib2(>=0.5.0)
Provides: remoteobjects
